setup.cfg
setup.py
ninjalog/__init__.py
ninjalog.egg-info/PKG-INFO
ninjalog.egg-info/SOURCES.txt
ninjalog.egg-info/dependency_links.txt
ninjalog.egg-info/requires.txt
ninjalog.egg-info/top_level.txt