Metadata-Version: 1.0
Name: ninjalog
Version: 0.3
Summary: A Python logging handler for https://www.ninjalog.io
Home-page: https://www.ninjalog.io
Author: Tyson Holub
Author-email: tyson@tysonholub.com
License: MIT
Platform: UNKNOWN
